azure/ai/inference/__init__.py
azure/ai/inference/_client.py
azure/ai/inference/_configuration.py
azure/ai/inference/_model_base.py
azure/ai/inference/_patch.py
azure/ai/inference/_serialization.py
azure/ai/inference/_vendor.py
azure/ai/inference/_version.py
azure/ai/inference/py.typed
azure/ai/inference/tracing.py
azure/ai/inference/_operations/__init__.py
azure/ai/inference/_operations/_operations.py
azure/ai/inference/_operations/_patch.py
azure/ai/inference/aio/__init__.py
azure/ai/inference/aio/_client.py
azure/ai/inference/aio/_configuration.py
azure/ai/inference/aio/_patch.py
azure/ai/inference/aio/_vendor.py
azure/ai/inference/aio/_operations/__init__.py
azure/ai/inference/aio/_operations/_operations.py
azure/ai/inference/aio/_operations/_patch.py
azure/ai/inference/models/__init__.py
azure/ai/inference/models/_enums.py
azure/ai/inference/models/_models.py
azure/ai/inference/models/_patch.py
azure/ai/inference/prompts/__init__.py
azure/ai/inference/prompts/_core.py
azure/ai/inference/prompts/_invoker.py
azure/ai/inference/prompts/_mustache.py
azure/ai/inference/prompts/_parsers.py
azure/ai/inference/prompts/_patch.py
azure/ai/inference/prompts/_prompty_utils.py
azure/ai/inference/prompts/_renderers.py
azure/ai/inference/prompts/_tracer.py
azure/ai/inference/prompts/_utils.py
azure_ai_inference-1.0.0b8.dist-info/LICENSE
azure_ai_inference-1.0.0b8.dist-info/METADATA
azure_ai_inference-1.0.0b8.dist-info/WHEEL
azure_ai_inference-1.0.0b8.dist-info/top_level.txt
azure_ai_inference-1.0.0b8.dist-info/RECORD
