Metadata-Version: 2.1
Name: azure-ai-inference
Version: 1.0.0b8
Summary: Microsoft Azure AI Inference Client Library for Python
Home-page: https://github.com/Azure/azure-sdk-for-python/tree/main/sdk/ai/azure-ai-inference
Author: Microsoft Corporation
Author-email: azpysdkhelp@microsoft.com
License: MIT License
Keywords: azure,azure sdk
Classifier: Development Status :: 4 - Beta
Classifier: Programming Language :: Python
Classifier: Programming Language :: Python :: 3 :: Only
Classifier: Programming Language :: Python :: 3
Classifier: Programming Language :: Python :: 3.8
Classifier: Programming Language :: Python :: 3.9
Classifier: Programming Language :: Python :: 3.10
Classifier: Programming Language :: Python :: 3.11
Classifier: Programming Language :: Python :: 3.12
Classifier: License :: OSI Approved :: MIT License
Requires-Python: >=3.8
License-File: LICENSE
Requires-Dist: isodate>=0.6.1
Requires-Dist: azure-core>=1.30.0
Requires-Dist: typing-extensions>=4.6.0
Provides-Extra: opentelemetry
Requires-Dist: azure-core-tracing-opentelemetry; extra == "opentelemetry"
Provides-Extra: prompts
Requires-Dist: pyyaml; extra == "prompts"
